torchq/__init__.py
torchq-0.0.1.dist-info/LICENSE
torchq-0.0.1.dist-info/WHEEL
torchq-0.0.1.dist-info/METADATA
torchq-0.0.1.dist-info/RECORD
