Metadata-Version: 2.1
Name: torchq
Version: 0.0.1
Summary: PyTorch Quantization Book
Author-email: xinetzone <735613050@qq.com>
Maintainer-email: xinetzone <735613050@qq.com>
Requires-Python: >=3.8
Classifier: Development Status :: 4 - Beta
Classifier: Programming Language :: Python :: 3
Classifier: Framework :: Sphinx
Classifier: Framework :: Sphinx :: Theme
Classifier: License :: OSI Approved :: Apache Software License
Classifier: Operating System :: OS Independent
Requires-Dist: d2py
Requires-Dist: pydata_sphinx_theme
Requires-Dist: pytest-cov ; extra == "coverage"
Requires-Dist: codecov ; extra == "coverage"
Requires-Dist: torchq[test] ; extra == "coverage"
Requires-Dist: pyyaml ; extra == "dev"
Requires-Dist: pre-commit ; extra == "dev"
Requires-Dist: torchq[coverage] ; extra == "dev"
Requires-Dist: myst-nb ; extra == "doc"
Requires-Dist: pytest ; extra == "doc"
Requires-Dist: pytest-regressions ; extra == "doc"
Requires-Dist: sphinxext-rediraffe ; extra == "doc"
Requires-Dist: sphinx_copybutton ; extra == "doc"
Requires-Dist: pytest ; extra == "test"
Requires-Dist: torchq[doc] ; extra == "test"
Project-URL: Home, https://github.com/xinetzone/torch-qat
Provides-Extra: coverage
Provides-Extra: dev
Provides-Extra: doc
Provides-Extra: test
